Metadata-Version: 2.1
Name: aiida-qp2
Version: 0.2.0
Summary: AiiDA plugin for the Quantum Package 2.0
Home-page: https://github.com/TREX-CoE/aiida-qp2
Author: Evgeny Posenitskiy
Author-email: posenitskiy@irsamc.ups-tlse.fr
License: MIT
Platform: UNKNOWN
Classifier: Development Status :: 4 - Beta
Classifier: Programming Language :: Python
Classifier: Intended Audience :: Science/Research
Classifier: License :: OSI Approved :: MIT License
Classifier: Framework :: AiiDA
Provides-Extra: testing
Provides-Extra: pre-commit
Provides-Extra: docs
License-File: LICENSE
